frykit/__init__.py
frykit/calc.py
frykit/conf.py
frykit/image.py
frykit/plot/__init__.py
frykit/plot/api.py
frykit/plot/artist.py
frykit/plot/projection.py
frykit/plot/typing.py
frykit/plot/utils.py
frykit/prof.py
frykit/py.typed
frykit/shp/__init__.py
frykit/shp/binary.py
frykit/shp/data.py
frykit/shp/mask.py
frykit/shp/typing.py
frykit/shp/utils.py
frykit/typing.py
frykit/utils.py
frykit-0.8.0.dist-info/licenses/LICENSE
frykit-0.8.0.dist-info/WHEEL
frykit-0.8.0.dist-info/METADATA
frykit-0.8.0.dist-info/RECORD
