Metadata-Version: 2.4
Name: frykit
Version: 0.8.0
Summary: A simple toolbox for Matplotib and Cartopy
Author: ZhaJiMan
Author-email: ZhaJiMan <915023793@qq.com>
License-Expression: MIT
License-File: LICENSE
Classifier: Programming Language :: Python :: 3
Classifier: Programming Language :: Python :: 3.10
Classifier: Programming Language :: Python :: 3.11
Classifier: Programming Language :: Python :: 3.12
Classifier: Programming Language :: Python :: 3.13
Classifier: Topic :: Scientific/Engineering :: GIS
Classifier: Topic :: Scientific/Engineering :: Visualization
Classifier: Operating System :: OS Independent
Requires-Dist: typing-extensions>=4.13.0
Requires-Dist: pandas>=2.0.0
Requires-Dist: shapely>=2.0.0
Requires-Dist: cartopy>=0.22.0
Requires-Dist: frykit-data==0.1.0 ; extra == 'data'
Requires-Python: >=3.10
Project-URL: Changelog, https://github.com/ZhaJiMan/frykit/blob/main/CHANGELOG.md
Project-URL: Homepage, https://github.com/ZhaJiMan/frykit
Project-URL: Issues, https://github.com/ZhaJiMan/frykit/issues
Provides-Extra: data
